<?xml version="1.0" encoding="utf-8"?>
<CanvasApp xmlns:xsi="http://www.w3.org/2001/XMLSchema-instance">
  <Name>tyt_travelerapp_7735a</Name>
  <AppVersion>2020-09-09T01:44:01Z</AppVersion>
  <Status>Ready</Status>
  <CreatedByClientVersion>3.20083.24.0</CreatedByClientVersion>
  <MinClientVersion>3.20083.24.0</MinClientVersion>
  <Tags>{"primaryDeviceWidth":"640","primaryDeviceHeight":"1136","sienaVersion":"20200909T014401Z-3.20083.24.0","deviceCapabilities":"","supportsPortrait":"true","supportsLandscape":"false","primaryFormFactor":"Phone","publisherVersion":"3.20083.24","minimumRequiredApiVersion":"2.2.0","hasComponent":"true","hasUnlockedComponent":"true","isUnifiedRootApp":"false"}</Tags>
  <IsCdsUpgraded>0</IsCdsUpgraded>
  <GalleryItemId xsi:nil="true"></GalleryItemId>
  <BackgroundColor>rgba(208, 52, 56, 1)</BackgroundColor>
  <DisplayName>Traveler App</DisplayName>
  <Description xsi:nil="true"></Description>
  <CommitMessage xsi:nil="true"></CommitMessage>
  <Publisher xsi:nil="true"></Publisher>
  <AuthorizationReferences xsi:nil="true"></AuthorizationReferences>
  <ConnectionReferences>{"b67034b6-d1d3-4655-9ed5-2e71e281cf08":{"id":"/providers/microsoft.powerapps/apis/shared_cognitiveservicescustomvision","displayName":"Custom Vision","iconUri":"https://connectoricons-prod.azureedge.net/releases/v1.0.1373/1.0.1373.2081/cognitiveservicescustomvision/icon.png","dataSources":["CustomVision"],"dependencies":[],"dependents":[],"parameterHints":{},"isOnPremiseConnection":false,"sharedConnectionId":"97ceba12-683d-4f9b-93f1-b837aabe80c2","bypassConsent":false,"dataSets":{},"apiTier":"Standard"}}</ConnectionReferences>
  <DatabaseReferences>{"default.cds":{"databaseDetails":{"referenceType":"Environmental","environmentName":"default.cds"},"dataSources":{"Dealers":{"entitySetName":"tyt_dealers","logicalName":"tyt_dealer"},"Vehicles":{"entitySetName":"tyt_vehicles","logicalName":"tyt_vehicle"},"Accessories":{"entitySetName":"tyt_accessories","logicalName":"tyt_accessory"},"Vehicle Delivery Requests":{"entitySetName":"tyt_vehicledeliveryrequests","logicalName":"tyt_vehicledeliveryrequest"},"Vehicle Delivery Request Accessories":{"entitySetName":"tyt_vehicledeliveryrequestaccessories","logicalName":"tyt_vehicledeliveryrequestaccessory"}}}}</DatabaseReferences>
  <CanConsumeAppPass>0</CanConsumeAppPass>
  <BypassConsent>0</BypassConsent>
  <AdminControlBypassConsent>0</AdminControlBypassConsent>
  <EmbeddedApp xsi:nil="true"></EmbeddedApp>
  <IntroducedVersion>1.0</IntroducedVersion>
  <CdsDependencies>{"cdsdependencies":[{"logicalname":"tyt_dealer","componenttype":1},{"logicalname":"tyt_vehicle","componenttype":1},{"logicalname":"tyt_accessory","componenttype":1},{"logicalname":"tyt_vehicledeliveryrequest","componenttype":1},{"logicalname":"tyt_vehicledeliveryrequestaccessory","componenttype":1}]}</CdsDependencies>
  <IsCustomizable>1</IsCustomizable>
  <BackgroundImageUri>/CanvasApps/tyt_travelerapp_7735a_BackgroundImageUri</BackgroundImageUri>
  <DocumentUri>/CanvasApps/tyt_travelerapp_7735a_DocumentUri.msapp</DocumentUri>
</CanvasApp>